aneki/__init__.py
aneki/core.py
aneki/main.py
aneki/parsers.py
aneki/shytok_net.cert
aneki-0.3.1.dist-info/METADATA
aneki-0.3.1.dist-info/RECORD
aneki-0.3.1.dist-info/WHEEL
aneki-0.3.1.dist-info/entry_points.txt
aneki-0.3.1.dist-info/top_level.txt
