Metadata-Version: 2.1
Name: aneki
Version: 0.3.1
Summary: Aneki = jokes delivery
Home-page: https://github.com/VolkovAK/aneki
Author: VolkovAK
License: UNKNOWN
Platform: UNKNOWN
Classifier: Programming Language :: Python :: 3
Classifier: License :: OSI Approved :: GNU General Public License v3 (GPLv3)
Classifier: Operating System :: OS Independent
Requires-Python: >=3.5
Requires-Dist: requests
